azure_blob/__init__.py
azure_blob/azure_blob.py
azure_blob/blobio.py
azure_blob/config.py
azure_blob/py.typed
azure_blob/storage.py
azure_blob/workflow.py
azure_blob_tui-0.1.2.dist-info/METADATA
azure_blob_tui-0.1.2.dist-info/WHEEL
azure_blob_tui-0.1.2.dist-info/entry_points.txt
azure_blob_tui-0.1.2.dist-info/licenses/LICENSE
azure_blob_tui-0.1.2.dist-info/RECORD
