Metadata-Version: 2.4
Name: azure-blob-tui
Version: 0.1.2
Summary: changeme
Project-URL: Repository, https://github.com/leo1oel/azure-blob-tui
Author-email: leo1oel <liuym23@mails.tsinghua.edu.cn>
License-Expression: MIT
License-File: LICENSE
Classifier: Development Status :: 4 - Beta
Classifier: Intended Audience :: Developers
Classifier: Operating System :: OS Independent
Classifier: Programming Language :: Python
Classifier: Programming Language :: Python :: 3
Classifier: Programming Language :: Python :: 3.11
Classifier: Programming Language :: Python :: 3.12
Classifier: Programming Language :: Python :: 3.13
Classifier: Programming Language :: Python :: 3.14
Classifier: Typing :: Typed
Requires-Python: <4.0,>=3.11
Requires-Dist: azstoragetorch>=0.2.0
Requires-Dist: azure-storage-blob>=12.24.0
Requires-Dist: cryptography>=46.0.3
Requires-Dist: platformdirs>=4.3.0
Requires-Dist: textual>=7.3.0
